{
  "dob": "undefined-undefined-1946",
  "title": "Awad Olwan",
  "date": "2020-08-14",
  "playlistId": "3bc5rKbAqGP2SDbM7IyzuG",
  "imageurl": "https://static-cdn.sr.se/images/2071/b20493a2-ea70-412c-81e5-f1e1ddf6452b.jpg?preset=api-default-square",
  "episodeUrl": "https://sverigesradio.se/avsnitt/1518815",
  "tracks": [
    {
      "track": {
        "id": "50CjXiDFzVBVvwNv0LxAm3",
        "name": "Sing Me Back Home"
      },
      "duration_ms": 238990,
      "artists": [
        {
          "name": "Don Williams",
          "id": "4Ti0EKl2PVEms2NRMVGqNe"
        }
      ],
      "album": {
        "id": "4OJ1zJCzIkLBmhki2oeKMd",
        "name": "Reflections",
        "img": "https://i.scdn.co/image/ab67616d000048517940cf1a329bfd66ef61c4c7"
      },
      "release_date": "2014-01-01",
      "popularity": 44
    },
    {
      "track": {
        "id": "2Kz4F0d2tveAas7QG33RPj",
        "name": "When I Need You - Live"
      },
      "duration_ms": 247226,
      "artists": [
        {
          "name": "Leo Sayer",
          "id": "04LIHk1SobiQwt2tlupoAV"
        }
      ],
      "album": {
        "id": "4D2fgAlZKeO6DRJhWTkIKP",
        "name": "Leo Sayer (Live)",
        "img": "https://i.scdn.co/image/ab67616d0000485132d86c4e1a1a962243a18724"
      },
      "release_date": "2009-01-01",
      "popularity": 52
    },
    {
      "track": {
        "id": "1VMYy1ayXtVt1Jx7JJryZm",
        "name": "Den jag kunde va"
      },
      "duration_ms": 238680,
      "artists": [
        {
          "name": "Hoola Bandoola Band",
          "id": "5nKrlPFxyS6Al128p3vQG7"
        }
      ],
      "album": {
        "id": "0jG1Xq6a89ZxXO3DClQOw7",
        "name": "1971-2011",
        "img": "https://i.scdn.co/image/ab67616d000048513d09ffb3966f67bcaf920c79"
      },
      "release_date": "2011-01-01",
      "popularity": 32
    },
    {
      "track": {
        "id": "3W6E0EIMLTn8fUjOhjAjcX",
        "name": "Wand'rin' Star (From the \"Amazon Prime - Dog With A Bad Leg\" TV Advert)"
      },
      "duration_ms": 264869,
      "artists": [
        {
          "name": "Lee Marvin",
          "id": "7GbjN1ab1LJcJV2JOhTqBK"
        }
      ],
      "album": {
        "id": "2aT7GlbvfY2I9dMhO2VsTx",
        "name": "Wand'rin' Star (From the \"Amazon Prime - Dog With A Bad Leg\" TV Advert)",
        "img": "https://i.scdn.co/image/ab67616d00004851842621f70d000cab198500fb"
      },
      "release_date": "2015-08-12",
      "popularity": 34
    },
    {
      "track": {
        "id": "2Dsw0QFS4kM6o4XjlQiRRQ",
        "name": "Mustapha"
      },
      "duration_ms": 166611,
      "artists": [
        {
          "name": "Bob Azzam",
          "id": "6aHHLKbMeqAmTkdwcogHjE"
        }
      ],
      "album": {
        "id": "3jCrdWXShgNRz8mBWM5iDJ",
        "name": "Tres Chic",
        "img": "https://i.scdn.co/image/ab67616d00004851a0486d6cf7dce3770cd1d2b5"
      },
      "release_date": "2012-07-10",
      "popularity": 25
    },
    {
      "track": {
        "id": "1hXxIhG7vUfwLlTh9imMST",
        "name": "Jag tror på sommaren"
      },
      "duration_ms": 207733,
      "artists": [
        {
          "name": "Mats Olin",
          "id": "5HfK3VuVDpr1eCeYgE6h7Z"
        }
      ],
      "album": {
        "id": "0l537xeeUQXZAkArjKmb2H",
        "name": "Sommar, sommar, sommar",
        "img": "https://i.scdn.co/image/ab67616d00004851ec33b6331501e4f4fcc2ff1d"
      },
      "release_date": "1997-01-01",
      "popularity": 32
    },
    {
      "track": {
        "id": "1PtJclc46wTk367PlsU6Uj",
        "name": "I Have A Dream"
      },
      "duration_ms": 285413,
      "artists": [
        {
          "name": "ABBA",
          "id": "0LcJLqbBmaGUft1e9Mm8HV"
        }
      ],
      "album": {
        "id": "7iLuHJkrb9KHPkMgddYigh",
        "name": "Voulez-Vous",
        "img": "https://i.scdn.co/image/ab67616d00004851aa22899360d8ba6704732dec"
      },
      "release_date": "1979",
      "popularity": 63
    },
    {
      "track": {
        "id": "5odXFIUE5YFAbA7iEdL0w8",
        "name": "Tusen bitar"
      },
      "duration_ms": 276559,
      "artists": [
        {
          "name": "Björn Afzelius",
          "id": "0PXQ16KY3iwdfvluCikdn0"
        }
      ],
      "album": {
        "id": "2CU896kswgsU4w2VWHbbub",
        "name": "Tusen bitar",
        "img": "https://i.scdn.co/image/ab67616d00004851a0955427ff70077701c7fda2"
      },
      "release_date": "1990-01-01",
      "popularity": 48
    },
    {
      "track": {
        "id": "4VJrTc5QPr13zgkwxaTjjN",
        "name": "Little Boxes"
      },
      "duration_ms": 114773,
      "artists": [
        {
          "name": "Pete Seeger",
          "id": "1P9syEkl41IFowWIJN7ZBY"
        }
      ],
      "album": {
        "id": "1ggnnzHVxJFuTDIY78ZF1R",
        "name": "Headlines and Footnotes: A Collection of Topical Songs",
        "img": "https://i.scdn.co/image/ab67616d00004851923085005648d417752508da"
      },
      "release_date": "1999-05-18",
      "popularity": 45
    },
    {
      "track": {
        "id": "3DJJaahjp6HqRo9B23H36e",
        "name": "En sång om frihet"
      },
      "duration_ms": 302215,
      "artists": [
        {
          "name": "Sven-Bertil Taube",
          "id": "7Gl6zw4YYJQ1CAgs7oEBPY"
        }
      ],
      "album": {
        "id": "7mNV8U2sBdTH1tvQy7yPVz",
        "name": "Big-5 : Sven-Bertil Taube",
        "img": "https://i.scdn.co/image/ab67616d00004851daa7db3a7af460e4a59df6a8"
      },
      "release_date": "2010-11-26",
      "popularity": 26
    }
  ]
}