[
  {
    "trackId": "4SszGQQUkTxFCce9KFiNmz",
    "name": "Přísahám, odcházím",
    "duration_ms": 180000,
    "artist": "Michael",
    "artistId": "1xEX8WPnrFYKbyjLNx23Mj",
    "albumId": "34CK9zNIPCPxcW7Xm2GnpA",
    "release_date": "2022-04-08",
    "popularity": 9
  },
  {
    "trackId": "2xiOdusRnZezQok1RgLNeS",
    "name": "You Should Be Dancing - Edit / From \"Saturday Night Fever\" Soundtrack",
    "duration_ms": 256493,
    "artist": "Bee Gees",
    "artistId": "1LZEQNv7sE11VDY3SdxQeN",
    "albumId": "4V8z8vZUCyYUBlUI9CfSbY",
    "release_date": "1976-01-01",
    "popularity": 68
  },
  {
    "trackId": "0jNUF9U7qZdYmcQvBUmt6e",
    "name": "Dance",
    "duration_ms": 227933,
    "artist": "Matteo Saggese",
    "artistId": "3svbV9ROns7csbmy5yVLm4",
    "albumId": "4HHfbKO3CQIx2zEgqqTWv6",
    "release_date": "2004",
    "popularity": 14
  },
  {
    "trackId": "7LVHVU3tWfcxj5aiPFEW4Q",
    "name": "Fix You",
    "duration_ms": 295533,
    "artist": "Coldplay",
    "artistId": "4gzpq5DPGxSnKTe4SA8HAU",
    "albumId": "4E7bV0pzG0LciBSWTszra6",
    "release_date": "2005-06-07",
    "popularity": 82
  },
  {
    "trackId": "2Cd9iWfcOpGDHLz6tVA3G4",
    "name": "Waka Waka (This Time for Africa) [The Official 2010 FIFA World Cup (TM) Song] (feat. Freshlyground)",
    "duration_ms": 202626,
    "artist": "Shakira",
    "artistId": "0EmeFodog0BfCgMzAIvKQp",
    "albumId": "3pzQF7YgU1f66pBayA8uHv",
    "release_date": "2010-05-07",
    "popularity": 79
  },
  {
    "trackId": "5WzHOXXyk3ZrchtVr5pnxz",
    "name": "Gianni Schicchi: Aria. \"O mio babbino caro\"",
    "duration_ms": 143440,
    "artist": "Giacomo Puccini",
    "artistId": "0OzxPXyowUEQ532c9AmHUR",
    "albumId": "0h8iIqw8uv8Rif7zPK8iml",
    "release_date": "2010-07-26",
    "popularity": 8
  },
  {
    "trackId": "7MdenVOyOCRoxbgPpjEiAL",
    "name": "They Don't Care About Us - Remastered Version",
    "duration_ms": 284560,
    "artist": "Michael Jackson",
    "artistId": "3fMbdgg4jU18AjLCKBhRSm",
    "albumId": "7pMVCMwGykuEu9rzTHxLCm",
    "release_date": "2009",
    "popularity": 52
  },
  {
    "trackId": "5hV0uMeGIUtKASyf25htAo",
    "name": "Caruso",
    "duration_ms": 319493,
    "artist": "Lucio Dalla",
    "artistId": "25MkkfEousyfp2eyh38FUl",
    "albumId": "01gyhMRB3RBxhgkfqbBNVi",
    "release_date": "1988-01-01",
    "popularity": 45
  },
  {
    "trackId": "26apsKYaTsoDdoIi22hZr3",
    "name": "En dans på rosor",
    "duration_ms": 184346,
    "artist": "Benny Anderssons Orkester",
    "artistId": "5KcJSAFLAEtpCkK5EI0KLS",
    "albumId": "0IpwjWmQNt0ceesV6p629y",
    "release_date": "2004",
    "popularity": 11
  },
  {
    "trackId": "612VcBshQcy4mpB2utGc3H",
    "name": "Tears in Heaven - Acoustic; Live at MTV Unplugged, Bray Film Studios, Windsor, England, UK, 1/16/1992; 2013 Remaster",
    "duration_ms": 280000,
    "artist": "Eric Clapton",
    "artistId": "6PAt558ZEZl0DmdXlnjMgD",
    "albumId": "3ebyEGol0Abc7VAxYf7vEg",
    "release_date": "1992-08-25",
    "popularity": 70
  },
  {
    "trackId": "6RUHYAHxHw1bY010mAcav0",
    "name": "Dansk balettmästare Hans Christian Lindeman",
    "duration_ms": 401506,
    "artist": "Hasse Alfredson",
    "artistId": "7bQVHmJKaxiXYkZ2miMrwb",
    "albumId": "05HMvwEjtYKNX6XGmStv7g",
    "release_date": "2008-01-01",
    "popularity": 12
  },
  {
    "trackId": "2KExvYsXyoFU8xp8I1K4EW",
    "name": "St. Matthew Passion, BWV 244 / Part Two: No.39 Aria (Alto): \"Erbarme dich\"",
    "duration_ms": 455360,
    "artist": "Johann Sebastian Bach",
    "artistId": "5aIqB5nVVvmFsvSdExz408",
    "albumId": "0dXHsb4nUzPpyZ5sTeAMqw",
    "release_date": "2006-03-15",
    "popularity": 22
  },
  {
    "trackId": "1HHeOs6zRdF8Ck58easiAY",
    "name": "Alejandro",
    "duration_ms": 274213,
    "artist": "Lady Gaga",
    "artistId": "1HY2Jd0NmPuamShAr6KMms",
    "albumId": "6rePArBMb5nLWEaY9aQqL4",
    "release_date": "2009-11-05",
    "popularity": 70
  },
  {
    "trackId": "5uCoHAAGFt2LBtyVCB3SQm",
    "name": "Walk Like A Man",
    "duration_ms": 141040,
    "artist": "Jackpots",
    "artistId": "70rHU9zUYScq6sCE9xn1kQ",
    "albumId": "77j1E8aqEqdzGIh3lYimY2",
    "release_date": "2003-01-01",
    "popularity": 3
  },
  {
    "trackId": "3CMVjlbvNJMHDfYPX7xCpi",
    "name": "It's Oh So Quiet",
    "duration_ms": 218733,
    "artist": "Björk",
    "artistId": "7w29UYBi0qsHi5RTcv3lmA",
    "albumId": "3p7WXDBxhC5KS9IFXnwae7",
    "release_date": "1995-06-13",
    "popularity": 57
  },
  {
    "trackId": "4atI4s4twgaBjdjfupti2e",
    "name": "Just In Time - 1998 Remaster",
    "duration_ms": 144133,
    "artist": "Frank Sinatra",
    "artistId": "1Mxqyy3pSjf8kZZL4QVxS0",
    "albumId": "2XgFfM6SNKtNLGcN3joZro",
    "release_date": "1959",
    "popularity": 52
  }
]