[{"trackId":"5d3kBmxHuMkHLmgXuCK30M","name":"Wake Me Up","duration_ms":211960,"artist":"Madilyn Bailey","artistId":"0NxhAEPOSeCg6vypFr7yjU","albumId":"3UeQky60klTQg4svlsc0yT","release_date":"2013-09-13","popularity":42},{"trackId":"1aMvViuAn7i8gRapm8C0p8","name":"Beautiful Day","duration_ms":212257,"artist":"Joshua Radin","artistId":"7omzannyG2lfDqP5xyZo34","albumId":"0NdOAkRDjeYoAgYFmpqUa5","release_date":"2013-05-07","popularity":50},{"trackId":"1szqiUxttcIKxfKuZkvy50","name":"You and Me (In My Pocket)","duration_ms":197353,"artist":"Milow","artistId":"6mo0UbyIvIePdXNyLwQlk5","albumId":"1tLRmJtVKmXsTqYQCJCmaA","release_date":"2011","popularity":38},{"trackId":"5eJ314ozT4CTPlyjdsGq78","name":"Utan dina andetag","duration_ms":264066,"artist":"kent","artistId":"4KXp3xtaz1wWXnu5u34eVX","albumId":"7mfwgTEuC1G6kj0BNovhS0","release_date":"1997-10-06","popularity":52},{"trackId":"5T8EDUDqKcs6OSOwEsfqG7","name":"Don't Stop Me Now - Remastered 2011","duration_ms":209413,"artist":"Queen","artistId":"1dfeR4HaWDbWqFHLkxsg1d","albumId":"2yuTRGIackbcReLUXOYBqU","release_date":"1978-11-10","popularity":81},{"trackId":"5Ph6PEwstaIE06vSMQwcR6","name":"Little Snitch","duration_ms":307305,"artist":"Lunatic","artistId":"1fNRWcD8JbU7aTvhxFp9qx","albumId":"7F774C4gnvhkeH4EcIiIJS","release_date":"2017-03-22","popularity":1},{"trackId":"53QF56cjZA9RTuuMZDrSA6","name":"I Won't Give Up","duration_ms":240165,"artist":"Jason Mraz","artistId":"4phGZZrJZRo4ElhRtViYdl","albumId":"64SChsjQBiEe3aVTFYnW1b","release_date":"2012-04-13","popularity":70},{"trackId":"7nLMZKhfkFZLr9rz4VyOpF","name":"Vart jag mig i världen vänder","duration_ms":212109,"artist":"Den svenska björnstammen","artistId":"0NyrvUybTePmsuED5vZi4G","albumId":"5GkyGLEWLO3RNzZAmOZgLt","release_date":"2012-01-01","popularity":59},{"trackId":"7vu0JkJh0ldukEYbTVcqd0","name":"Issues","duration_ms":176320,"artist":"Julia Michaels","artistId":"0ZED1XzwlLHW4ZaG4lOT6m","albumId":"1qyjZGIeeLJlXbYWuoloWj","release_date":"2017-07-28","popularity":72},{"trackId":"36lkJSDyMEZoWTqtRj8Q8q","name":"You're the Inspiration - 2006 Remaster","duration_ms":229240,"artist":"Chicago","artistId":"3iDD7bnsjL9J4fO298r0L0","albumId":"1ICKrl6sDjJD1YdR9VDfPR","release_date":"1984-05-14","popularity":72},{"trackId":"5v55pDsyrxIs6OTk3E5l69","name":"Rullar fram","duration_ms":228920,"artist":"Fronda","artistId":"4i6VLJAtySJ3Vxf9R1me6p","albumId":"2u9ZI8Xqe2RqzRw7R4Kc0I","release_date":"2007-09-19","popularity":50},{"trackId":"7LMtp4HBhWLQ2P2POPn6li","name":"7 Years","duration_ms":237266,"artist":"Lukas Graham","artistId":"25u4wHJWxCA9vO0CzxAbK7","albumId":"0o2W2d2Zl7Bur5jph6phkm","release_date":"2016-04-01","popularity":58},{"trackId":"73bzcsDjx9FqzqKWcPLMiH","name":"Stop Loving You","duration_ms":269226,"artist":"TOTO","artistId":"0PFtn5NtBbbUNbU9EAmIWF","albumId":"7LVxCg18peWcBBdu7Xr6r3","release_date":"1988-03-01","popularity":62},{"trackId":"5Yx5PhdnwhNzLMBl34TZw4","name":"Both Sides Now","duration_ms":273573,"artist":"Joni Mitchell","artistId":"5hW4L92KnC6dX9t7tYM4Ve","albumId":"02piRJBAWgCu2Et3rOkK4w","release_date":"2019-02-15","popularity":58}]