[{"trackId":"1fX0h6SaZBXwmr4haRvirQ","name":"Nah Neh Nah","duration_ms":174533,"artist":"Vaya Con Dios","artistId":"0ODWsmNXtn928qhhEn87C8","albumId":"3FteFh6UKUrLciSCBjMsmO","release_date":"1990-04-10","popularity":58},{"trackId":"7fLbCGlipM2zblhppk4mFJ","name":"Dom där jag kommer från","duration_ms":334986,"artist":"Håkan Hellström","artistId":"3H7Ez7cwaYw4L3ELy4v3Lc","albumId":"2nOzYO8LlFATIKd9S3qNUt","release_date":"2010-10-13","popularity":42},{"trackId":"1J4r8qdu9ORx8e7aB4WiLs","name":"Candy","duration_ms":182480,"artist":"Two White Horses","artistId":"33yVXViQZCoVeaNPE48eFq","albumId":"4l7sYSRlFFv6BIukmhEWOD","release_date":"2009-01-01","popularity":0},{"trackId":"3ebOJcNrx3BTGNPkHcsn68","name":"Pappa","duration_ms":354866,"artist":"Ola Magnell","artistId":"0EcjEGUjRcoFoVinJpwi91","albumId":"4SxDqdOTDrkv2A1erLHqsQ","release_date":"1975","popularity":23},{"trackId":"0yGoMpm5Aa4jD0dQpuPNcK","name":"Break Dance Party - Original Version 1984","duration_ms":395133,"artist":"Break Machine","artistId":"3iRV02DBgHoXH9J8Gqfd7M","albumId":"5pggQZgmxlW0sVs72y0IYS","release_date":"1984","popularity":27},{"trackId":"4hHtOF9xG8PlwRi4AgXYlU","name":"Fotografiskt Minne","duration_ms":232066,"artist":"Mattias Alkberg","artistId":"5p8AjcGi5g19fWNvC2zhqE","albumId":"3eSVDID7U4iPkISNnd44ed","release_date":"2005-09-15","popularity":2},{"trackId":"3X4JH0aBqKKAamYkpj5xer","name":"Did You Give the World Some Love Today, Baby","duration_ms":199049,"artist":"Doris","artistId":"4oNCFX4cbl6Jy1VANKiE6A","albumId":"5ihQ4Gepi7qXFrKqVF5shn","release_date":"1970","popularity":38},{"trackId":"1fX0h6SaZBXwmr4haRvirQ","name":"Nah Neh Nah","duration_ms":174533,"artist":"Vaya Con Dios","artistId":"0ODWsmNXtn928qhhEn87C8","albumId":"3FteFh6UKUrLciSCBjMsmO","release_date":"1990-04-10","popularity":58}]