[
  {
    "trackId": "4WY0rvaDS9iln4ZtabOykQ",
    "name": "The High Mass: Kyrie: Kyrie eleison (Chorus)",
    "duration_ms": 364160,
    "artist": "Sven-David Sandström",
    "artistId": "00AUnQaXE6XTTZvr7kgNHb",
    "albumId": "4AIbIriejFw6CTvzoXhIUh",
    "release_date": "1995-01-01",
    "popularity": 0
  },
  {
    "trackId": "5qwjH4yeWHPiClYdMnEeiA",
    "name": "Räggibitn'",
    "duration_ms": 201108,
    "artist": "Lindbärs",
    "artistId": "4unYZH2ygRDILvplbLN5FN",
    "albumId": "49iOhHH8vvkOGYijzkkeBm",
    "release_date": "2021-04-14",
    "popularity": 39
  },
  {
    "trackId": "7pipz88aN0avbIYusF70Tu",
    "name": "The High Mass (Excerpts): IIIb. Credo. Crucifixus",
    "duration_ms": 286266,
    "artist": "Sven-David Sandström",
    "artistId": "00AUnQaXE6XTTZvr7kgNHb",
    "albumId": "2FoYko0hrkXT6xsu0oA5TE",
    "release_date": "2021-03-19",
    "popularity": 0
  },
  {
    "trackId": "5nRFn9AaiHsl0f3uo6d2ki",
    "name": "Till Havs",
    "duration_ms": 136760,
    "artist": "Jussi Björling & Nils Grevillius Orchestra",
    "artistId": "264175n225eFvqtFTF9XOU",
    "albumId": "5VIAGRLS99mg0RpCiILjPb",
    "release_date": "2009-03-10",
    "popularity": 15
  },
  {
    "trackId": "7Kz4f9CgtAfbmPBMX5q2ZV",
    "name": "La Voix",
    "duration_ms": 177013,
    "artist": "Malena Ernman",
    "artistId": "0muluUHym4N0wB62sD0MPo",
    "albumId": "0h8iIqw8uv8Rif7zPK8iml",
    "release_date": "2010-07-26",
    "popularity": 36
  },
  {
    "trackId": "46myjng22bqiMChbgDHLQj",
    "name": "Fantasiresan - För sömn och vila",
    "duration_ms": 917773,
    "artist": "Christina Divén",
    "artistId": "3SFF7ZOtYEQrZjroJBoBTN",
    "albumId": "2JR2YxeRd61izoiDpF7F6N",
    "release_date": "1997-01-01",
    "popularity": 25
  },
  {
    "trackId": "1MwVOQPwBmJFDshhtxtuER",
    "name": "Matthäus-Passion, BWV 244 / Erster Teil: No. 1 \"Kommt, ihr Töchter, helft mir klagen\"",
    "duration_ms": 419000,
    "artist": "Johann Sebastian Bach",
    "artistId": "5aIqB5nVVvmFsvSdExz408",
    "albumId": "5YbjOf1fj1Q1ZbfCNMiF3W",
    "release_date": "2013-01-01",
    "popularity": 6
  },
  {
    "trackId": "7647WNclsrXgytRPOvrOKj",
    "name": "Kom till mig",
    "duration_ms": 187773,
    "artist": "Sven-David Sandström",
    "artistId": "00AUnQaXE6XTTZvr7kgNHb",
    "albumId": "6Sls5Dl5h8gYpwInvqs2pA",
    "release_date": "2011-01-01",
    "popularity": 0
  },
  {
    "trackId": "2SRXbLBCJ5Fu91hxJAVPtl",
    "name": "Jeg elsker dig (I love thee), Op.5, No.3",
    "duration_ms": 102013,
    "artist": "Edvard Grieg",
    "artistId": "5ihY290YPGc3aY2xTyx7Gy",
    "albumId": "2FFK5R5xwX0yNpPhykcnjr",
    "release_date": "2000-01-01",
    "popularity": 1
  },
  {
    "trackId": "47jlmGhTc6AjGppeHPJmUq",
    "name": "Hälsingland",
    "duration_ms": 203606,
    "artist": "Maskinisten",
    "artistId": "7EqcInpJPb4pRMPyEvUKRR",
    "albumId": "2a48lh4Xr6WA9BYAEhLQUq",
    "release_date": "2018-10-09",
    "popularity": 33
  },
  {
    "trackId": "0XWMAEcZMjs43rIWJA4d37",
    "name": "Marlowe's Theme",
    "duration_ms": 316933,
    "artist": "Putte Wickman",
    "artistId": "6sx2v1gYnSUlkVO7M5Mk95",
    "albumId": "4oAp1NxlZbuTzSOfZjzlCX",
    "release_date": "2004-01-01",
    "popularity": 19
  },
  {
    "trackId": "2p7zP8FPUzbRLyD498is2z",
    "name": "In paradisum",
    "duration_ms": 278120,
    "artist": "Sven-David Sandström",
    "artistId": "00AUnQaXE6XTTZvr7kgNHb",
    "albumId": "4iN8IOCvqQhIrsvfexd2y5",
    "release_date": "2019-11-15",
    "popularity": 5
  },
  {
    "trackId": "3dc3X4Qi9CaaSBMnsdMBP1",
    "name": "Någonstans bland alla skuggorna",
    "duration_ms": 190866,
    "artist": "Einar Ekberg",
    "artistId": "0BZKPU9xjUNwHWkMPXR1Uu",
    "albumId": "1iOWbOSt0Na3t29JK2099F",
    "release_date": "1991-01-01",
    "popularity": 2
  }
]