{
  "dob": "1978-12-04",
  "title": "Herman Geijer",
  "date": "2015-07-15",
  "playlistId": "1RzdoYgosgH3fOoUKOyUI9",
  "imageurl": "https://static-cdn.sr.se/images/2071/3528741_2048_1152.jpg?preset=api-default-square",
  "episodeUrl": "https://sverigesradio.se/avsnitt/576702",
  "tracks": [
    {
      "track": {
        "id": "3cw08kUGnAI7vxrlAuuWy4",
        "name": "Zombi - Originale"
      },
      "duration_ms": 264253,
      "artists": [
        {
          "name": "Goblin",
          "id": "7H92g6n1BvyzvQwaERZKZl"
        }
      ],
      "album": {
        "id": "05ptZhBxx90o7nQRK4Q76f",
        "name": "Zombi",
        "img": "https://i.scdn.co/image/ab67616d000048518e3e710dd543a6acd1311e67"
      },
      "release_date": "1998-01-31",
      "popularity": 21
    },
    {
      "track": {
        "id": "7vFYpl5n3ZRhWsWBpKSaOr",
        "name": "Don Abandons Alice"
      },
      "duration_ms": 176412,
      "artists": [
        {
          "name": "John Murphy",
          "id": "4UGoqrmNHDJ166XD6DtZni"
        }
      ],
      "album": {
        "id": "2Ea7bxHYGb5tqUGdUgpmAf",
        "name": "Don Abandons Alice",
        "img": "https://i.scdn.co/image/ab67616d000048514c6113256d15d7bf0da94ce0"
      },
      "release_date": "2013-11-18",
      "popularity": 38
    },
    {
      "track": {
        "id": "0cCi1Gf9lHNf6s17GwreLa",
        "name": "La rage"
      },
      "duration_ms": 242266,
      "artists": [
        {
          "name": "Keny Arkana",
          "id": "0Q5EUbHvUWlYpSwmKKbUSF"
        }
      ],
      "album": {
        "id": "0NVMD77N6PJHoKRugFmr8q",
        "name": "Entre ciment et belle étoile",
        "img": "https://i.scdn.co/image/ab67616d0000485101481d03c32d8ef0f44eac7e"
      },
      "release_date": "2006-10-16",
      "popularity": 43
    },
    {
      "track": {
        "id": "6sjGsKuInpaK3uoaWGe22W",
        "name": "Från och med Du"
      },
      "duration_ms": 193360,
      "artists": [
        {
          "name": "Oskar Linnros",
          "id": "3E8Mx37sikkaFoX5DRecLi"
        }
      ],
      "album": {
        "id": "2jCYbQBRefZrTeMXIMIsNp",
        "name": "Vilja Bli",
        "img": "https://i.scdn.co/image/ab67616d00004851a11d74ed7e8d845053c1096d"
      },
      "release_date": "2010-01-01",
      "popularity": 57
    },
    {
      "track": {
        "id": "6v3RR0KUcqFzqucljqvwAb",
        "name": "Demon"
      },
      "duration_ms": 197800,
      "artists": [
        {
          "name": "Entombed",
          "id": "2pnezMcaiTHfGmgmGQjLsB"
        }
      ],
      "album": {
        "id": "1CZwyjL96gGx4PryOIFNYn",
        "name": "Wolverine Blues",
        "img": "https://i.scdn.co/image/ab67616d000048518caf88d5a1f7574c17614803"
      },
      "release_date": "1993-10-04",
      "popularity": 30
    },
    {
      "track": {
        "id": "21PIM2hC989Gfio7G8u2KA",
        "name": "Långt där ute"
      },
      "duration_ms": 356240,
      "artists": [
        {
          "name": "Siri Karlsson",
          "id": "6EMgtAWgzWSwrAJ9Pp7aeO"
        }
      ],
      "album": {
        "id": "0urnOJIQjZ9QxnbRcuFlyL",
        "name": "The Lost Colony",
        "img": "https://i.scdn.co/image/ab67616d0000485155c4f17fd47889d7468b6f95"
      },
      "release_date": "2015-02-20",
      "popularity": 3
    },
    {
      "track": {
        "id": "0Tmh2wYoJNaTF8WzkeRFmN",
        "name": "Tänker på dig"
      },
      "duration_ms": 323986,
      "artists": [
        {
          "name": "KSMB",
          "id": "5umOft7CgVOutNpa0rGX71"
        }
      ],
      "album": {
        "id": "5OIjMvwTnIMLO77zk7VBQX",
        "name": "Förord till livet/Tänker på dig",
        "img": "https://i.scdn.co/image/ab67616d00004851fac639a0456b4073652f67b0"
      },
      "release_date": "1981-01-01",
      "popularity": 14
    },
    {
      "track": {
        "id": "3slxYrFpg9bplFb94Ne2g6",
        "name": "Welcome Home"
      },
      "duration_ms": 276400,
      "artists": [
        {
          "name": "King Diamond",
          "id": "5i0ph60TnwTlIGrOZAmcZa"
        }
      ],
      "album": {
        "id": "24Q1XHD9hhZl5FULWmG58H",
        "name": "Them",
        "img": "https://i.scdn.co/image/ab67616d00004851212d65beb8d383e3f1b791e5"
      },
      "release_date": "1988-09-13",
      "popularity": 40
    },
    {
      "track": {
        "id": "0kgnQSWcZWmqFyjlKbgXc2",
        "name": "Trollmannen Lurifiks"
      },
      "duration_ms": 140000,
      "artists": [
        {
          "name": "Anita Hegerland",
          "id": "43hIlZ3UX4EjCiHijBmDHy"
        }
      ],
      "album": {
        "id": "3SDUNb7gUIu05mxhlr7hXY",
        "name": "Anitas Beste Barnesanger",
        "img": "https://i.scdn.co/image/ab67616d000048510a713e93125e49c2781bc1d9"
      },
      "release_date": "2000-01-01",
      "popularity": 22
    },
    {
      "track": {
        "id": "3PRGcLvFKBGcG5LMer7rn7",
        "name": "All About Us"
      },
      "duration_ms": 180960,
      "artists": [
        {
          "name": "t.A.T.u.",
          "id": "2Q3eZMfDQgT8MhPowKFXYO"
        }
      ],
      "album": {
        "id": "1IzFFToDvhT3gnZ2ZpyXUi",
        "name": "Dangerous and Moving",
        "img": "https://i.scdn.co/image/ab67616d0000485132416982d2ea14bc8c2fe852"
      },
      "release_date": "2005-01-01",
      "popularity": 57
    },
    {
      "track": {
        "id": "7phS2dSHIDjWmKo3FsxkjC",
        "name": "Beväpna Er"
      },
      "duration_ms": 214625,
      "artists": [
        {
          "name": "Ladomir",
          "id": "15HUUK40NXtHiV3odNyq0I"
        }
      ],
      "album": {
        "id": "7u7J3TkEYsmmZpmtLxgtdK",
        "name": "Tro Mig (1987)",
        "img": "https://i.scdn.co/image/ab67616d000048519609da0366af25de96833103"
      },
      "release_date": "1987",
      "popularity": 0
    },
    {
      "track": {
        "id": "4fiOTntQKr24p07FvQDHZE",
        "name": "Raining Blood"
      },
      "duration_ms": 255186,
      "artists": [
        {
          "name": "Slayer",
          "id": "1IQ2e1buppatiN1bxUVkrk"
        }
      ],
      "album": {
        "id": "5v5BfkxWDAKTkzrXl3H0mU",
        "name": "Reign In Blood (Expanded)",
        "img": "https://i.scdn.co/image/ab67616d000048511530f31c8d4197777b70ee5d"
      },
      "release_date": "1986-01-01",
      "popularity": 64
    }
  ]
}