[{"trackId":"3Lk7RWStfLaHG7lXsuS87j","name":"One","duration_ms":260466,"artist":"Mary J. Blige","artistId":"1XkoF8ryArs86LZvFOkbyr","albumId":"13HYuDhB1soZvHzwoymXoV","release_date":"2005-01-01","popularity":64},{"trackId":"3AfeqqbWGlrJjOICHxUpCk","name":"Heaven's Open - 2000 Remaster","duration_ms":271666,"artist":"Mike Oldfield","artistId":"562Od3CffWedyz2BbeYWVn","albumId":"2P4gGEWFH9zpJFXiLVRAJR","release_date":"2000-01-01","popularity":28},{"trackId":"5fmvZgUFuUq1SnzT3S6y4o","name":"Ring Ring - English Version","duration_ms":184733,"artist":"ABBA","artistId":"0LcJLqbBmaGUft1e9Mm8HV","albumId":"1pVtxVKXwhU2nsvrTI1WqT","release_date":"1973","popularity":55},{"trackId":"5Gti7ED5ilOIsYCSouxKBl","name":"Bara lite mig","duration_ms":239973,"artist":"Vera","artistId":"0BXZupDIadYPMR02ycdur3","albumId":"1tDuzpoCcTYEb4p2QEEkJi","release_date":"2006-01-01","popularity":0},{"trackId":"21NPhKvaZdnmBWxo0CYVJ4","name":"Amanda","duration_ms":179639,"artist":"Jimmy Jansson","artistId":"3i7yhYt2s1AK269jue0DDs","albumId":"7CSIQLO2OpfI9ZuVFmdp4V","release_date":"2007-01-01","popularity":34},{"trackId":"6wpGqhRvJGNNXwWlPmkMyO","name":"I Still Haven't Found What I'm Looking For","duration_ms":277476,"artist":"U2","artistId":"51Blml2LZPmy7TTiAg47vQ","albumId":"5y6wlw1LnqFnQFruMeiwGU","release_date":"1987-03-03","popularity":77},{"trackId":"0W1uTK6I97CbjFKAVtRGfK","name":"Too Much Love Will Kill You - Remastered 2011","duration_ms":259213,"artist":"Queen","artistId":"1dfeR4HaWDbWqFHLkxsg1d","albumId":"391ScNR3xKywWSpfDwP3n0","release_date":"1995-11-06","popularity":62},{"trackId":"72BnKkKnrOeCDY9vy2avFk","name":"Ti Sento","duration_ms":255000,"artist":"Matia Bazar","artistId":"449mAbddAC2PAgNM3TLyc5","albumId":"7fK9JzCaIIIWehaWd7IoUE","release_date":"1991-01-01","popularity":56},{"trackId":"2FTZeRHQ4gRPViPMpWL9uX","name":"I'm Alive","duration_ms":210226,"artist":"Céline Dion","artistId":"4S9EykWXhStSc15wEx8QFK","albumId":"1YQ5V21NSxR9ZauQ3RUbfZ","release_date":"2001-01-01","popularity":67},{"trackId":"2kvg4AwMIstkygdQhfFfSf","name":"Calleth You, Cometh I","duration_ms":272360,"artist":"The Ark","artistId":"73ib5ljBj2xAIR7R3hTwF4","albumId":"2853c5Z7BEfJCaFltIQ0C7","release_date":"2002-08-26","popularity":48},{"trackId":"4aLcGMxwFtcZRpl7NDtNW2","name":"Time To Say Goodbye","duration_ms":245893,"artist":"Francesco Sartori","artistId":"0VtVDsLKIsyiBa1DeAdKbU","albumId":"6O4lYKMQFLDcaUrBocYSRz","release_date":"2007-01-01","popularity":59}]